ez_telegram/__init__.py
ez_telegram-0.1.0.dist-info/LICENSE
ez_telegram-0.1.0.dist-info/METADATA
ez_telegram-0.1.0.dist-info/WHEEL
ez_telegram-0.1.0.dist-info/top_level.txt
ez_telegram-0.1.0.dist-info/RECORD
