Metadata-Version: 2.1
Name: ez_telegram
Version: 0.1.0
Summary: Minimalist client to get messages from public telegram channels, without tokens/sessions.
Author: Scr44gr
Author-email: <scr44gr@protonmail.com>
Keywords: telegram,client,simple,webscraping
Classifier: Development Status :: 3 - Alpha
Classifier: Programming Language :: Python :: 3
Classifier: Operating System :: MacOS :: MacOS X
Classifier: Operating System :: Microsoft :: Windows
License-File: LICENSE
Requires-Dist: bs4
Requires-Dist: requests
Requires-Dist: lxml
Requires-Dist: markdownify
